redxaieasyfunctions/__init__.py
redxaieasyfunctions/core.py
redxaieasyfunctions-1.0.5.dist-info/licenses/LICENSE
redxaieasyfunctions-1.0.5.dist-info/METADATA
redxaieasyfunctions-1.0.5.dist-info/WHEEL
redxaieasyfunctions-1.0.5.dist-info/top_level.txt
redxaieasyfunctions-1.0.5.dist-info/RECORD
