Metadata-Version: 2.4
Name: RedXAIEasyFunctions
Version: 1.0.5
Summary: A toolkit to simplify and enhance basic functions.
Author-email: MainDirectory <RedXDevelopment1998@gmail.com>
Classifier: Programming Language :: Python :: 3
Classifier: License :: OSI Approved :: MIT License
Requires-Python: >=3.7
License-File: LICENSE
Dynamic: license-file
